{
  "type": "tconstruct:material",
  "conditions": [
    {
      "type": "forge:not",
      "value": {
        "type": "forge:tag_empty",
        "tag": "forge:storage_blocks/soul_stained_steel"
      }
    },
    {
      "type": "forge:mod_loaded",
      "modid": "malum"
    }
  ],
  "ingredient": {
    "tag": "forge:storage_blocks/soul_stained_steel"
  },
  "leftover": {
    "count": 1,
    "tag": "forge:ingots/soul_stained_steel"
  },
  "material": "tcintegrations:soul_stained_steel",
  "needed": 1,
  "value": 9
}